skillfs/__init__.py
skillfs/constants.py
skillfs/py.typed
skillfs/mcp/__init__.py
skillfs/mcp/connection_manager.py
skillfs/mcp/generate_tool_wrapper.py
skillfs/mcp/server_manager.py
skillfs/repositories/__init__.py
skillfs/repositories/constants.py
skillfs/repositories/git_repo.py
skillfs/runners/__init__.py
skillfs/runners/base.py
skillfs/runners/providers/__init__.py
skillfs/runners/providers/anthropic.py
skillfs/runners/tools/__init__.py
skillfs/runners/tools/base.py
skillfs/runners/tools/edit_file.py
skillfs/runners/tools/glob.py
skillfs/runners/tools/grep.py
skillfs/runners/tools/load_skill.py
skillfs/runners/tools/read_file.py
skillfs/runners/tools/run_command.py
skillfs/runners/tools/subrunner.py
skillfs/runners/tools/write_file.py
skillfs/runners/types/__init__.py
skillfs/runners/types/main/__init__.py
skillfs/runners/types/main/runner.py
skillfs/runners/types/search/__init__.py
skillfs/runners/types/search/runner.py
skillfs/runners/types/search/system_prompt.py
skillfs/sandboxes/__init__.py
skillfs/sandboxes/base.py
skillfs/sandboxes/e2b.py
skillfs/skills/__init__.py
skillfs/skills/catalog.py
skillfs/skills/parser.py
skillfs/storage/__init__.py
skillfs/storage/base.py
skillfs/storage/gcs.py
skillfs/storage/local.py
skillfs/workspaces/__init__.py
skillfs/workspaces/git_commit.py
skillfs/workspaces/persistence.py
skillfs/workspaces/workspace.py
skillfs-0.1.0.dist-info/METADATA
skillfs-0.1.0.dist-info/WHEEL
skillfs-0.1.0.dist-info/RECORD
