Metadata-Version: 2.4
Name: skillfs
Version: 0.1.0
Summary: Add your description here
Requires-Python: >=3.10
Requires-Dist: anthropic>=0.75.0
Requires-Dist: e2b-code-interpreter
Requires-Dist: httpx>=0.27.0
Requires-Dist: mcp>=1.0.0
Requires-Dist: pydantic>=2.0.0
Requires-Dist: python-dotenv
Requires-Dist: pyyaml>=6.0.3
Provides-Extra: dev
Requires-Dist: mypy>=1.0.0; extra == 'dev'
Requires-Dist: pytest>=7.0.0; extra == 'dev'
Requires-Dist: ruff>=0.1.0; extra == 'dev'
Provides-Extra: gcs
Requires-Dist: google-cloud-storage>=3.6.0; extra == 'gcs'
